galsen_game_of_life/__init__.py
galsen_game_of_life/__main__.py
galsen_game_of_life/core_functions.py
galsen_game_of_life-1.1.dist-info/LICENSE
galsen_game_of_life-1.1.dist-info/METADATA
galsen_game_of_life-1.1.dist-info/WHEEL
galsen_game_of_life-1.1.dist-info/entry_points.txt
galsen_game_of_life-1.1.dist-info/top_level.txt
galsen_game_of_life-1.1.dist-info/RECORD
