Metadata-Version: 2.1
Name: galsen-game-of-life
Version: 1.1
Summary: Game of life version galsen
Home-page: https://github.com/abdoufermat5/conway-game-of-life
Author: abdoufermat
License: GPLv3
Keywords: game of life,game,python,algorithm
Classifier: Development Status :: 3 - Alpha
Classifier: Intended Audience :: Developers
Classifier: Topic :: Games/Entertainment :: Simulation
Classifier: License :: OSI Approved :: GNU General Public License v3 (GPLv3)
Classifier: Programming Language :: Python :: 3.8
License-File: LICENSE
